[{"cid": "QmPLG5wAmn1HvdmCTKMUFxfLGkaFeJbmDiEoUbBMKSLSxz", "dur": 420, "ts": 1636264903.281, "upload_date": "2021-11-07", "category": "trending", "local_check_ts": 1637283812.208074, "public_check_ts": 1637283813.0909858, "local_data": {"overhead": 4.482592, "download_time": 42.068128, "file_size": 270177456.0, "video_length": 420, "stall_rate": 0, "bandwidth": 6422378.861260477}, "public_data": {"overhead": 0.167419, "download_time": 0.0006189999999999807, "file_size": 169.0, "video_length": 420, "stall_rate": 0, "bandwidth": 273021.0016155174}}, {"cid": "QmZVPPNknoCCT5ZmuzY41socuWHQTfLcNhEKbKpgDRRWAR", "dur": 60, "ts": 1636064232.714, "upload_date": "2021-11-04", "category": "trending", "local_check_ts": null, "public_check_ts": 1637283938.0702624, "local_data": null, "public_data": {"overhead": 0.316412, "download_time": 3.637406, "file_size": 8713381.0, "video_length": 60, "stall_rate": 0, "bandwidth": 2395493.106900907}}, {"cid": "QmVJubna4FMsbTbVUWRJ31tF9HYRsUd1aavBzHr2WEXy3i", "dur": 3, "ts": 1636233272.653, "upload_date": "2021-11-06", "category": "trending", "local_check_ts": null, "public_check_ts": 1637284058.6879542, "local_data": null, "public_data": {"overhead": 0.26791, "download_time": 0.11736400000000002, "file_size": 404812.0, "video_length": 3, "stall_rate": 0, "bandwidth": 3449200.7770696287}}, {"cid": "QmdtfwNASEvUFAXZMW9iUztKs8u6ZVYbi3i5i7xynddFX5", "dur": 96, "ts": 1636210231.603, "upload_date": "2021-11-06", "category": "trending", "local_check_ts": null, "public_check_ts": 1637284185.031905, "local_data": null, "public_data": {"overhead": 0.457977, "download_time": 5.114344, "file_size": 13799581.0, "video_length": 96, "stall_rate": 0, "bandwidth": 2698211.344407025}}, {"cid": "QmY8yxu62RaZdHZjmLXQnSjwmLPfa4bddp78LRfcwzuAPy", "dur": 223, "ts": 1636117616.611, "upload_date": "2021-11-05", "category": "trending", "local_check_ts": null, "public_check_ts": 1637284325.8076062, "local_data": null, "public_data": {"overhead": 0.197724, "download_time": 19.864666, "file_size": 31937552.0, "video_length": 223, "stall_rate": 0, "bandwidth": 1607756.807992644}}, {"cid": "QmWeKYuYN3xzbZ8VPybQAWVa85Tq9wSscRKG3brWSKAd1J", "dur": 78, "ts": 1636301008.297, "upload_date": "2021-11-07", "category": "new", "local_check_ts": null, "public_check_ts": 1637284446.497509, "local_data": null, "public_data": {"overhead": 0.338335, "download_time": 0.0006090000000000262, "file_size": 169.0, "video_length": 78, "stall_rate": 0, "bandwidth": 277504.1050903}}, {"cid": "QmU1v7dFtTZupMhwideeVJVTiwgEQA6Fc41Ad3DJEEg7GV", "dur": 766, "ts": 1636296815.393, "upload_date": "2021-11-07", "category": "new", "local_check_ts": null, "public_check_ts": 1637284567.4808364, "local_data": null, "public_data": {"overhead": 0.141701, "download_time": 0.0006570000000000187, "file_size": 169.0, "video_length": 766, "stall_rate": 0, "bandwidth": 257229.83257229102}}, {"cid": "QmTZVg7zbKwQWdLwLqb7X1n93t3hkcjsmD11MxFrqNhLqo", "dur": 197, "ts": 1636214879.695, "upload_date": "2021-11-06", "category": "hot", "local_check_ts": null, "public_check_ts": 1637284739.6548948, "local_data": null, "public_data": {"overhead": 3.025396, "download_time": 48.123675, "file_size": 17937984.0, "video_length": 197, "stall_rate": 0, "bandwidth": 372747.59253111907}}, {"cid": "Qmf58wr2wtxKNc3bdzM2MEPdggn5aQyee1eyYbe9h3g5Fr", "dur": 213, "ts": 1636328154.113, "upload_date": "2021-11-07", "category": "trending", "local_check_ts": null, "public_check_ts": 1637284917.085518, "local_data": null, "public_data": {"overhead": 0.809871, "download_time": 56.321540999999996, "file_size": 31788462.0, "video_length": 213, "stall_rate": 0, "bandwidth": 564410.3736437183}}, {"cid": "QmcgUkwKAfxP2GMrhpDKMJXzB8CNefuwbdRmHwjWof1rD6", "dur": 751, "ts": 1636313014.396, "upload_date": "2021-11-07", "category": "new", "local_check_ts": null, "public_check_ts": 1637285038.3511791, "local_data": null, "public_data": {"overhead": 0.144694, "download_time": 0.0005600000000000049, "file_size": 169.0, "video_length": 751, "stall_rate": 0, "bandwidth": 301785.71428571164}}, {"cid": "QmfSSagzeVWtH13wiqQAmUbGeEXLRqmueyxuTotrkKJKbz", "dur": 1351, "ts": 1636407524.784, "upload_date": "2021-11-08", "category": "trending", "local_check_ts": null, "public_check_ts": 1637285159.791406, "local_data": null, "public_data": {"overhead": 0.420612, "download_time": 0.0006390000000000007, "file_size": 169.0, "video_length": 1351, "stall_rate": 0, "bandwidth": 264475.7433489825}}, {"cid": "QmYKGfnMc4Pz4DBjsLrNmTqzjNm1YmBvqtgTMoQV9HCCZ2", "dur": 550, "ts": 1636353039.762, "upload_date": "2021-11-08", "category": "trending", "local_check_ts": 1637285193.4529662, "public_check_ts": 1637285194.2987983, "local_data": {"overhead": 7.662333, "download_time": 25.411914, "file_size": 355168212.0, "video_length": 550, "stall_rate": 0, "bandwidth": 13976444.749498209}, "public_data": {"overhead": 0.270267, "download_time": 0.0006059999999999954, "file_size": 169.0, "video_length": 550, "stall_rate": 0, "bandwidth": 278877.88778878096}}, {"cid": "QmTdbNBJxXgE8aYxp86QA6jSKryQMLDuLhPJW3aYBfrANA", "dur": 82, "ts": 1636362321.39, "upload_date": "2021-11-08", "category": "trending", "local_check_ts": null, "public_check_ts": 1637285322.0289237, "local_data": null, "public_data": {"overhead": 0.463358, "download_time": 6.342222, "file_size": 11541619.0, "video_length": 82, "stall_rate": 0, "bandwidth": 1819806.8437213332}}, {"cid": "QmegXbacFu5VHsVvTiGR4AyUB8ZvCvcLANwWvweUuiCVAT", "dur": 27, "ts": 1636354289.813, "upload_date": "2021-11-08", "category": "trending", "local_check_ts": null, "public_check_ts": 1637285444.3282263, "local_data": null, "public_data": {"overhead": 0.396059, "download_time": 1.5534970000000001, "file_size": 4119588.0, "video_length": 27, "stall_rate": 0, "bandwidth": 2651815.8709028726}}, {"cid": "QmXPqDedk9fGyBCiff7GahcXYAqHrrZS3Kjgc69APborcv", "dur": 60, "ts": 1636383519.202, "upload_date": "2021-11-08", "category": "trending", "local_check_ts": null, "public_check_ts": 1637285572.0955942, "local_data": null, "public_data": {"overhead": 0.267506, "download_time": 7.280799, "file_size": 8776410.0, "video_length": 60, "stall_rate": 0, "bandwidth": 1205418.5261809865}}, {"cid": "QmPNSefoAxvJFQbUG5T7R31GxQsWqvEwvny8rzyQ3QnN3t", "dur": 11, "ts": 1636399221.898, "upload_date": "2021-11-08", "category": "trending", "local_check_ts": null, "public_check_ts": 1637285694.2030325, "local_data": null, "public_data": {"overhead": 0.499792, "download_time": 0.986853, "file_size": 1642962.0, "video_length": 11, "stall_rate": 0, "bandwidth": 1664849.7800584282}}, {"cid": "QmfPiXSPGXUcabhu9E5McYJLRmUzD26ybuQmNcuT9E6oF5", "dur": 61, "ts": 1636364642.54, "upload_date": "2021-11-08", "category": "trending", "local_check_ts": null, "public_check_ts": 1637285818.5494576, "local_data": null, "public_data": {"overhead": 0.26657, "download_time": 3.3886700000000003, "file_size": 8130509.0, "video_length": 61, "stall_rate": 0, "bandwidth": 2399321.562737003}}, {"cid": "QmYRPSpHkKHYZZvcNvR4Sckcdh5vSGyCCw1nsaE3xcsjh6", "dur": 300, "ts": 1636358808.19, "upload_date": "2021-11-08", "category": "trending", "local_check_ts": null, "public_check_ts": 1637285983.9774249, "local_data": null, "public_data": {"overhead": 1.278739, "download_time": 43.634029, "file_size": 43999978.0, "video_length": 300, "stall_rate": 0, "bandwidth": 1008386.7799602004}}, {"cid": "Qmce4qm7pzbE8Ht3ywxSnoHTvUZEjPbQQ2kN1FE56BpcLH", "dur": 31, "ts": 1636427565.704, "upload_date": "2021-11-09", "category": "new", "local_check_ts": null, "public_check_ts": 1637286105.8999884, "local_data": null, "public_data": {"overhead": 0.653277, "download_time": 0.853238, "file_size": 3041258.0, "video_length": 31, "stall_rate": 0, "bandwidth": 3564372.425981965}}, {"cid": "QmQdkp9RyR1GXXsmGBLViR7ubn9VMBJJXs3kLjdLieWN2v", "dur": 812, "ts": 1636424713.398, "upload_date": "2021-11-09", "category": "new", "local_check_ts": null, "public_check_ts": 1637286305.1133718, "local_data": null, "public_data": {"overhead": 0.351355, "download_time": 78.171434, "file_size": 33589770.0, "video_length": 812, "stall_rate": 0, "bandwidth": 429693.6653356007}}, {"cid": "QmQYBAwrrSjHf4xG6nwTGtkdveNYsH8V6HxnU6o29nYTvA", "dur": 1799, "ts": 1636413802.665, "upload_date": "2021-11-08", "category": "new", "local_check_ts": null, "public_check_ts": "", "local_data": null, "public_data": null}, {"cid": "QmfNsDCSw5UYgE8eWvPB7x24V6BiR6q29wqsdG8Yoj2e7X", "dur": 187, "ts": 1636412018.832, "upload_date": "2021-11-08", "category": "new", "local_check_ts": null, "public_check_ts": 1637286793.5001974, "local_data": null, "public_data": {"overhead": 0.379115, "download_time": 10.123752999999999, "file_size": 26996013.0, "video_length": 187, "stall_rate": 0, "bandwidth": 2666601.308822924}}, {"cid": "QmTLuxgcqjHicFyYqKEWgDUdsajeJr3WW4NujBakDgRHwk", "dur": 44, "ts": 1636409863.842, "upload_date": "2021-11-08", "category": "new", "local_check_ts": null, "public_check_ts": 1637286915.111922, "local_data": null, "public_data": {"overhead": 0.243105, "download_time": 0.48773, "file_size": 5682520.0, "video_length": 44, "stall_rate": 0, "bandwidth": 11650954.4215037}}, {"cid": "QmX5gJStgs8FPjDTW7vgYNfHnsLbRxTWQFM3fr9Q5Sxb3b", "dur": 154, "ts": 1636401395.01, "upload_date": "2021-11-08", "category": "new", "local_check_ts": null, "public_check_ts": 1637287059.4296844, "local_data": null, "public_data": {"overhead": 0.420949, "download_time": 23.446251, "file_size": 22568265.0, "video_length": 154, "stall_rate": 0, "bandwidth": 962553.2457193263}}, {"cid": "QmPyDWqWSYFHdFzr6SNknhDxfkRNJtz49z3Jfvms7k5sqa", "dur": 1127, "ts": 1636400969.42, "upload_date": "2021-11-08", "category": "new", "local_check_ts": null, "public_check_ts": 1637287188.750681, "local_data": null, "public_data": {"overhead": 8.990639, "download_time": 0.0004950000000008004, "file_size": 169.0, "video_length": 1127, "stall_rate": 0, "bandwidth": 341414.1414135894}}, {"cid": "QmUz5Qz4p1M5JoEw6j54h9D2ncTVhFZMNz1iZKV3mTn4AY", "dur": 111, "ts": 1636400510.672, "upload_date": "2021-11-08", "category": "new", "local_check_ts": null, "public_check_ts": 1637287324.8067975, "local_data": null, "public_data": {"overhead": 1.292003, "download_time": 13.576249, "file_size": 1838101.0, "video_length": 111, "stall_rate": 0, "bandwidth": 135390.93161888825}}, {"cid": "QmQUFwxPYpUmaHhNAqZVpoFwqN2yDMzwDnqSCxbrDG38nJ", "dur": 60, "ts": 1636465510.664, "upload_date": "2021-11-09", "category": "trending", "local_check_ts": null, "public_check_ts": 1637287455.8521433, "local_data": null, "public_data": {"overhead": 0.73295, "download_time": 9.986519999999999, "file_size": 8649947.0, "video_length": 60, "stall_rate": 0, "bandwidth": 866162.2867625561}}, {"cid": "QmYoiemzSwrPn6fkuiRscnp29gjDJ8KYgXaiBYc1ZH6PTy", "dur": 489, "ts": 1636443510.884, "upload_date": "2021-11-09", "category": "trending", "local_check_ts": 1637287488.129257, "public_check_ts": 1637287488.4522932, "local_data": {"overhead": 1.645234, "download_time": 30.242644000000002, "file_size": 315599607.0, "video_length": 489, "stall_rate": 0, "bandwidth": 10435582.517189965}, "public_data": {"overhead": 0.259571, "download_time": 0.0005729999999999902, "file_size": 169.0, "video_length": 489, "stall_rate": 0, "bandwidth": 294938.9179755722}}, {"cid": "QmYWCmkZMshRecp1sBXzdbDsEYkkqcJWUzVVxRsEnqndvx", "dur": 353, "ts": 1636483632.168, "upload_date": "2021-11-09", "category": "new", "local_check_ts": null, "public_check_ts": 1637287612.579846, "local_data": null, "public_data": {"overhead": 0.322915, "download_time": 2.889393, "file_size": 4128726.0, "video_length": 353, "stall_rate": 0, "bandwidth": 1428925.0371963938}}, {"cid": "QmXLrViJzjPgd4JEUguaLFM8e4sBYD1gJ5tu82CT2TGVXo", "dur": 63, "ts": 1636482095.901, "upload_date": "2021-11-09", "category": "new", "local_check_ts": null, "public_check_ts": 1637287752.3646908, "local_data": null, "public_data": {"overhead": 1.210684, "download_time": 17.603652, "file_size": 9368136.0, "video_length": 63, "stall_rate": 0, "bandwidth": 532170.0292643822}}, {"cid": "QmXBAmBK6b7xACdCYxqiP9UpC9cc6RrvigGkLG1Z34vYD4", "dur": 387, "ts": 1636450271.651, "upload_date": "2021-11-09", "category": "hot", "local_check_ts": null, "public_check_ts": 1637287977.2010677, "local_data": null, "public_data": {"overhead": 1.960563, "download_time": 102.494771, "file_size": 56785351.0, "video_length": 387, "stall_rate": 0, "bandwidth": 554031.6881141185}}, {"cid": "QmWjWcxcBQRVa22CNxmJqajdAiRZb2fuTDBTg3kWboEP6Z", "dur": 279, "ts": 1636428748.882, "upload_date": "2021-11-09", "category": "hot", "local_check_ts": null, "public_check_ts": 1637288189.7453024, "local_data": null, "public_data": {"overhead": 1.107655, "download_time": 90.311097, "file_size": 57899591.0, "video_length": 279, "stall_rate": 0, "bandwidth": 641112.6973687408}}, {"cid": "QmNwDbGfzFR1c7RpuBvpCRSB2m7E42txpd3Lm3fGwxQAy2", "dur": 172, "ts": 1636570843.023, "upload_date": "2021-11-10", "category": "trending", "local_check_ts": 1637288214.724424, "public_check_ts": 1637288215.1711326, "local_data": {"overhead": 6.934526, "download_time": 17.247355, "file_size": 17458911.0, "video_length": 172, "stall_rate": 0, "bandwidth": 1012265.9967281941}, "public_data": {"overhead": 0.396606, "download_time": 0.0005769999999999942, "file_size": 169.0, "video_length": 172, "stall_rate": 0, "bandwidth": 292894.28076256794}}, {"cid": "QmQvtqbU7dv6ctGj5TgJbTuThQGNtm2TJSwwZi9jMN6DCU", "dur": 56, "ts": 1636541171.812, "upload_date": "2021-11-10", "category": "trending", "local_check_ts": null, "public_check_ts": 1637288344.3836718, "local_data": null, "public_data": {"overhead": 0.564045, "download_time": 7.861108999999999, "file_size": 8315203.0, "video_length": 56, "stall_rate": 0, "bandwidth": 1057764.6232866128}}, {"cid": "QmVb1ZJQWo7xHoFJ7sFw1drBbD35PgdsDiXwGYxPoK9qgY", "dur": 666, "ts": 1636554616.982, "upload_date": "2021-11-10", "category": "trending", "local_check_ts": null, "public_check_ts": 1637288512.542597, "local_data": null, "public_data": {"overhead": 0.42379, "download_time": 46.957841, "file_size": 99315367.0, "video_length": 666, "stall_rate": 0, "bandwidth": 2114990.0609783144}}, {"cid": "QmRda5VctzuL5vkTw5Ni2jb3vTgZzmSNUjuivNMKrACc7s", "dur": 43, "ts": 1636588642.225, "upload_date": "2021-11-10", "category": "new", "local_check_ts": null, "public_check_ts": 1637288646.8159575, "local_data": null, "public_data": {"overhead": 0.602275, "download_time": 13.221822999999999, "file_size": 6161754.0, "video_length": 43, "stall_rate": 0, "bandwidth": 466029.0793485891}}, {"cid": "Qmcargu2p1HwSsJggGAdiMj8QSH9mFTFAt54ooR8RAPE91", "dur": 2518, "ts": 1636583636.138, "upload_date": "2021-11-10", "category": "new", "local_check_ts": null, "public_check_ts": 1637289175.8400853, "local_data": null, "public_data": {"overhead": 0.364605, "download_time": 408.106081, "file_size": 296787015.0, "video_length": 2518, "stall_rate": 0, "bandwidth": 727230.0728104073}}, {"cid": "QmS7dpHH5zYwfNLV4UcchjxhF8s8A9qcgj5QAUH64Qucj3", "dur": 2562, "ts": 1636580414.502, "upload_date": "2021-11-10", "category": "new", "local_check_ts": null, "public_check_ts": "", "local_data": null, "public_data": null}, {"cid": "QmSyMsRRrwtLBZ1a6b2siX6KWDBWzLiexxsqT9tNZ4bA83", "dur": 934, "ts": 1636578799.17, "upload_date": "2021-11-10", "category": "new", "local_check_ts": null, "public_check_ts": 1637289662.3855634, "local_data": null, "public_data": {"overhead": 0.374307, "download_time": 67.368317, "file_size": 138107146.0, "video_length": 934, "stall_rate": 0, "bandwidth": 2050031.1147746202}}, {"cid": "QmXAkpTGP9zpwSzoKKUMMWpUy6gRRkTkt7Ce8irED57BtP", "dur": 2498, "ts": 1636576528.564, "upload_date": "2021-11-10", "category": "new", "local_check_ts": null, "public_check_ts": 1637289945.8603055, "local_data": null, "public_data": {"overhead": 0.368672, "download_time": 162.69677099999998, "file_size": 292775752.0, "video_length": 2498, "stall_rate": 0, "bandwidth": 1799517.9019256628}}, {"cid": "QmejKQupE95tHQovue3t33RuQRQrDxGvzCDuLsebfvS5ZZ", "dur": 133, "ts": 1636576214.565, "upload_date": "2021-11-10", "category": "new", "local_check_ts": null, "public_check_ts": 1637290091.2201579, "local_data": null, "public_data": {"overhead": 2.768177, "download_time": 21.70204, "file_size": 8013418.0, "video_length": 133, "stall_rate": 0, "bandwidth": 369247.22284172365}}, {"cid": "QmUa1RUACz6MD2dv9pLQg1W6YoS1CHGkZs7Abpvx9BC84P", "dur": 241, "ts": 1636576033.406, "upload_date": "2021-11-10", "category": "new", "local_check_ts": null, "public_check_ts": 1637290254.8730593, "local_data": null, "public_data": {"overhead": 5.276371, "download_time": 37.677126, "file_size": 11138009.0, "video_length": 241, "stall_rate": 0, "bandwidth": 295617.26656114904}}, {"cid": "QmcXQ8zXcGEZKEcifzS48mNRJq6JZuPcQoEqBL1P7TWkAU", "dur": 317, "ts": 1636575909.622, "upload_date": "2021-11-10", "category": "new", "local_check_ts": null, "public_check_ts": 1637290408.0491817, "local_data": null, "public_data": {"overhead": 0.439951, "download_time": 32.466578999999996, "file_size": 18975398.0, "video_length": 317, "stall_rate": 0, "bandwidth": 584459.422102957}}, {"cid": "Qmcv531vMQUav1BbQoDZKkAD9j6QuBfs9wJaJT4xAYxsA1", "dur": 11, "ts": 1636573418.671, "upload_date": "2021-11-10", "category": "new", "local_check_ts": null, "public_check_ts": 1637290530.2938778, "local_data": null, "public_data": {"overhead": 0.55848, "download_time": 1.3977089999999999, "file_size": 1563733.0, "video_length": 11, "stall_rate": 0, "bandwidth": 1118782.9512437854}}, {"cid": "QmZmLpFR3CXKNVKayxsFEjuXy1syyGX729yTjrsAf5DRBL", "dur": 26, "ts": 1636573186.194, "upload_date": "2021-11-10", "category": "new", "local_check_ts": null, "public_check_ts": 1637290655.259008, "local_data": null, "public_data": {"overhead": 0.770644, "download_time": 3.973218, "file_size": 3466568.0, "video_length": 26, "stall_rate": 0, "bandwidth": 872483.7147118532}}, {"cid": "QmWGvQBAHNw3rAguL56eWFTRDVVumcWVYwhdLtXPNeraHn", "dur": 28, "ts": 1636572884.256, "upload_date": "2021-11-10", "category": "new", "local_check_ts": null, "public_check_ts": 1637290780.2400935, "local_data": null, "public_data": {"overhead": 0.337464, "download_time": 4.19461, "file_size": 3914581.0, "video_length": 28, "stall_rate": 0, "bandwidth": 933240.7542059929}}, {"cid": "QmaJnEM9xZYiPN7g7Q5UeUs4nrRBiP9L1RM5B36Co2t3TY", "dur": 17, "ts": 1636572624.558, "upload_date": "2021-11-10", "category": "new", "local_check_ts": null, "public_check_ts": 1637290906.0134196, "local_data": null, "public_data": {"overhead": 0.821405, "download_time": 4.309215999999999, "file_size": 2129595.0, "video_length": 17, "stall_rate": 0, "bandwidth": 494195.4638616399}}, {"cid": "QmZCez6zrKbxnRcN5y8nJ6y7w5maND1nvgkvqc1HMChcWn", "dur": 26, "ts": 1636572455.476, "upload_date": "2021-11-10", "category": "new", "local_check_ts": null, "public_check_ts": 1637291030.2219725, "local_data": null, "public_data": {"overhead": 0.526183, "download_time": 2.65138, "file_size": 3700084.0, "video_length": 26, "stall_rate": 0, "bandwidth": 1395531.3836568126}}, {"cid": "Qme859jmjz4EyDQXcwHzM8AH1FLSDQ6i24QEXLSuwaHxMP", "dur": 2494, "ts": 1636570456.567, "upload_date": "2021-11-10", "category": "new", "local_check_ts": null, "public_check_ts": "", "local_data": null, "public_data": null}, {"cid": "QmVPsVUPDbb9B6Kzsp1Zk2CNJzZ3YWyzSNUcxDADp3joHy", "dur": 864, "ts": 1636562180.363, "upload_date": "2021-11-10", "category": "new", "local_check_ts": null, "public_check_ts": 1637291766.8107758, "local_data": null, "public_data": {"overhead": 0.30179, "download_time": 112.291103, "file_size": 99274549.0, "video_length": 864, "stall_rate": 0, "bandwidth": 884082.0541232015}}, {"cid": "QmWbHayhbewi1x1agpvxi6s2AErxk29wT9oGf6JWAcdP67", "dur": 128, "ts": 1636648819.612, "upload_date": "2021-11-11", "category": "trending", "local_check_ts": null, "public_check_ts": 1637291918.769535, "local_data": null, "public_data": {"overhead": 0.419935, "download_time": 30.535221, "file_size": 27504031.0, "video_length": 128, "stall_rate": 0, "bandwidth": 900731.3554403291}}, {"cid": "QmPChbJ3imp3n8uD53u4RXNWR2qAPqTbTjn8AiQkwLyPJ4", "dur": 456, "ts": 1636618418.804, "upload_date": "2021-11-11", "category": "trending", "local_check_ts": null, "public_check_ts": 1637292040.6713378, "local_data": null, "public_data": {"overhead": 1.45687, "download_time": 0.0006279999999998509, "file_size": 169.0, "video_length": 456, "stall_rate": 0, "bandwidth": 269108.28025484097}}, {"cid": "QmQG6mGY8z8D67Z3EfwTYz2RkyANBETXmsHeNGNULGKR51", "dur": 22, "ts": 1636598421.826, "upload_date": "2021-11-11", "category": "trending", "local_check_ts": null, "public_check_ts": 1637292167.271931, "local_data": null, "public_data": {"overhead": 0.272754, "download_time": 5.6114310000000005, "file_size": 2832792.0, "video_length": 22, "stall_rate": 0, "bandwidth": 504825.23976504384}}, {"cid": "QmWPYwvDvtsiPFms1RcP4Kd5WBBk2yM6qreSMg6AB5LfhC", "dur": 344, "ts": 1636621562.082, "upload_date": "2021-11-11", "category": "trending", "local_check_ts": null, "public_check_ts": "", "local_data": null, "public_data": null}, {"cid": "QmeY7NJpopP41dkfWrMeo3wWVQtyp4dhNxqT9ieXPpYCD1", "dur": 13, "ts": 1636674968.754, "upload_date": "2021-11-11", "category": "trending", "local_check_ts": null, "public_check_ts": 1637292590.274281, "local_data": null, "public_data": {"overhead": 0.664315, "download_time": 2.455437, "file_size": 1816133.0, "video_length": 13, "stall_rate": 0, "bandwidth": 739637.384302672}}, {"cid": "QmavgPeM9N2bhPPoqdT9d3VHENef1yyaucAAdSRX1idCzL", "dur": 29, "ts": 1636629545.256, "upload_date": "2021-11-11", "category": "trending", "local_check_ts": null, "public_check_ts": 1637292716.7131255, "local_data": null, "public_data": {"overhead": 0.359169, "download_time": 5.022163, "file_size": 4194524.0, "video_length": 29, "stall_rate": 0, "bandwidth": 835202.6805979814}}, {"cid": "QmR9C5LJ1ZYpR9KbzrpT2YXvW88Z3NHPe8Z2dss83aHcNP", "dur": 357, "ts": 1636635418.249, "upload_date": "2021-11-11", "category": "trending", "local_check_ts": null, "public_check_ts": 1637292875.1505966, "local_data": null, "public_data": {"overhead": 0.282354, "download_time": 37.361964, "file_size": 52014589.0, "video_length": 357, "stall_rate": 0, "bandwidth": 1392180.2665405918}}, {"cid": "QmTwae2pPZ7LCj1Ewkg7tE3iB2QXpUb2Xd5auk7uNBEMKx", "dur": 65, "ts": 1636674820.732, "upload_date": "2021-11-11", "category": "new", "local_check_ts": null, "public_check_ts": 1637293012.024914, "local_data": null, "public_data": {"overhead": 0.690173, "download_time": 15.243199, "file_size": 9047836.0, "video_length": 65, "stall_rate": 0, "bandwidth": 593565.4320330004}}, {"cid": "QmVPX2nWTHdXtr8dWJSHfm8sPPP213YStinYYePujSh1Z9", "dur": 63, "ts": 1636674255.879, "upload_date": "2021-11-11", "category": "new", "local_check_ts": null, "public_check_ts": 1637293141.6133354, "local_data": null, "public_data": {"overhead": 0.604767, "download_time": 8.614151, "file_size": 8727315.0, "video_length": 63, "stall_rate": 0, "bandwidth": 1013136.9881953544}}, {"cid": "QmUkryfio7YbiKuPLo5f9aVcqWaCo6hrN8aCGeP5veZYj5", "dur": 1241, "ts": 1636668069.461, "upload_date": "2021-11-11", "category": "new", "local_check_ts": null, "public_check_ts": "", "local_data": null, "public_data": null}, {"cid": "Qme2ar738Y5FCpW9xqUEsuPBC4gRnRkpdWv3JAaRXcVUj4", "dur": 9, "ts": 1636667480.35, "upload_date": "2021-11-11", "category": "new", "local_check_ts": null, "public_check_ts": 1637293714.186345, "local_data": null, "public_data": {"overhead": 0.461808, "download_time": 0.206291, "file_size": 2474418.0, "video_length": 9, "stall_rate": 0, "bandwidth": 11994793.762209695}}, {"cid": "QmQcVF25pJdeo5E3BUPZrAsoYj973h2i863RatLxupggRK", "dur": 1047, "ts": 1636666752.39, "upload_date": "2021-11-11", "category": "new", "local_check_ts": null, "public_check_ts": 1637293838.4042008, "local_data": null, "public_data": {"overhead": 0.259465, "download_time": 3.4340859999999997, "file_size": 54653344.0, "video_length": 1047, "stall_rate": 0, "bandwidth": 15914960.778501181}}, {"cid": "QmfT7zUkLpMG15vXo7nMVAo9xHWGgwJrwJ1bAhZnRbkAGq", "dur": 217, "ts": 1636666643.649, "upload_date": "2021-11-11", "category": "new", "local_check_ts": null, "public_check_ts": 1637293977.3178244, "local_data": null, "public_data": {"overhead": 0.76416, "download_time": 17.284194, "file_size": 31869482.0, "video_length": 217, "stall_rate": 0, "bandwidth": 1843851.20879805}}, {"cid": "QmcS4Y5FRm1rZC1nzE1LspcyNie2Rucnx3f2EU5jBgg98v", "dur": 401, "ts": 1636665846.212, "upload_date": "2021-11-11", "category": "new", "local_check_ts": null, "public_check_ts": 1637294122.987922, "local_data": null, "public_data": {"overhead": 6.182105, "download_time": 19.248583, "file_size": 19717074.0, "video_length": 401, "stall_rate": 0, "bandwidth": 1024338.9864074669}}, {"cid": "QmT6K47aD1zDR1RjFBvY7CfJi8xvCQn1FoYaik64UbtRyU", "dur": 1409, "ts": 1636665520.043, "upload_date": "2021-11-11", "category": "new", "local_check_ts": null, "public_check_ts": 1637294324.6056995, "local_data": null, "public_data": {"overhead": 0.3107, "download_time": 80.531468, "file_size": 88525709.0, "video_length": 1409, "stall_rate": 0, "bandwidth": 1099268.5368656137}}, {"cid": "QmUPaSyhTDrtZA198VKhmBLFY31T5opeb7ZCMsdCwzEVcw", "dur": 2570, "ts": 1636662769.417, "upload_date": "2021-11-11", "category": "new", "local_check_ts": null, "public_check_ts": 1637294527.1793945, "local_data": null, "public_data": {"overhead": 0.286759, "download_time": 81.566833, "file_size": 300490247.0, "video_length": 2570, "stall_rate": 0, "bandwidth": 3683975.89986116}}, {"cid": "QmUexiM79LcdfMrpRkeh4E2a7JFqvuz5rBo6B5vJEufMqz", "dur": 160, "ts": 1636660680.05, "upload_date": "2021-11-11", "category": "new", "local_check_ts": null, "public_check_ts": 1637294658.8991277, "local_data": null, "public_data": {"overhead": 0.393302, "download_time": 10.403626, "file_size": 20032705.0, "video_length": 160, "stall_rate": 0, "bandwidth": 1925550.2841028697}}, {"cid": "QmfFSDaqfw3rbNxsssuPTv97YJ7ugGgr5BP6UiPo6rBc7x", "dur": 2505, "ts": 1636659505.521, "upload_date": "2021-11-11", "category": "new", "local_check_ts": null, "public_check_ts": 1637295076.7415657, "local_data": null, "public_data": {"overhead": 0.447415, "download_time": 297.01691100000005, "file_size": 294867513.0, "video_length": 2505, "stall_rate": 0, "bandwidth": 992763.3817456271}}, {"cid": "Qmd3tGstKEdTXM7zHd3n4BzwJKCpqX8LHXg8as3ha9uobX", "dur": 60, "ts": 1636637769.381, "upload_date": "2021-11-11", "category": "hot", "local_check_ts": null, "public_check_ts": 1637295203.3964822, "local_data": null, "public_data": {"overhead": 0.413553, "download_time": 5.483218, "file_size": 8487987.0, "video_length": 60, "stall_rate": 0, "bandwidth": 1547993.714639834}}, {"cid": "QmcsgQSeRmKdUcJuskSk1TYf5ZRqvt4irYfAAqtzhBsnoc", "dur": 636, "ts": 1636746462.519, "upload_date": "2021-11-12", "category": "trending", "local_check_ts": null, "public_check_ts": 1637295361.4612567, "local_data": null, "public_data": {"overhead": 0.256774, "download_time": 37.482531, "file_size": 92979328.0, "video_length": 636, "stall_rate": 0, "bandwidth": 2480604.3113790792}}, {"cid": "QmNLo4rwWnEpVPpP6591r4y1uJdnUWhd3terrHm9NXBb4T", "dur": 488, "ts": 1636707045.969, "upload_date": "2021-11-12", "category": "trending", "local_check_ts": null, "public_check_ts": 1637295482.7392213, "local_data": null, "public_data": {"overhead": 0.199995, "download_time": 0.0007079999999999864, "file_size": 169.0, "video_length": 488, "stall_rate": 0, "bandwidth": 238700.564971756}}, {"cid": "QmWzmPJv7SxvR3SCdRpSqDceKNSF7MocTcf6mgRuaFFVje", "dur": 60, "ts": 1636707613.932, "upload_date": "2021-11-12", "category": "trending", "local_check_ts": null, "public_check_ts": 1637295604.8249316, "local_data": null, "public_data": {"overhead": 0.182798, "download_time": 0.936224, "file_size": 8530963.0, "video_length": 60, "stall_rate": 0, "bandwidth": 9112096.036845883}}, {"cid": "QmZ9cvehCVHWTC9KWSFC7bSksM8edjxucVv1N5tnyZiVcB", "dur": 62, "ts": 1636707777.049, "upload_date": "2021-11-12", "category": "trending", "local_check_ts": null, "public_check_ts": 1637295742.1807153, "local_data": null, "public_data": {"overhead": 0.446204, "download_time": 15.744154, "file_size": 13487227.0, "video_length": 62, "stall_rate": 0, "bandwidth": 856649.8396801759}}, {"cid": "QmP4GXL99xp1mUNJ8gnQEFevCXDbcpUsmJr8jhiemyybw1", "dur": 1457, "ts": 1636759623.572, "upload_date": "2021-11-12", "category": "new", "local_check_ts": null, "public_check_ts": "", "local_data": null, "public_data": null}, {"cid": "QmZXKDTErdK99wCE897DXqruAJKdLfjXs8BewXGmTDmdPu", "dur": 65, "ts": 1636759608.468, "upload_date": "2021-11-12", "category": "new", "local_check_ts": null, "public_check_ts": 1637296341.3558407, "local_data": null, "public_data": {"overhead": 0.735115, "download_time": 2.454486, "file_size": 9443679.0, "video_length": 65, "stall_rate": 0, "bandwidth": 3847517.9732131287}}, {"cid": "QmNhhFGuug3eMPzJDNjScEp6kWXZhX5zGkquDLaRjudnyP", "dur": 65, "ts": 1636758511.966, "upload_date": "2021-11-12", "category": "new", "local_check_ts": null, "public_check_ts": 1637296465.347658, "local_data": null, "public_data": {"overhead": 0.990559, "download_time": 1.807008, "file_size": 4226010.0, "video_length": 65, "stall_rate": 0, "bandwidth": 2338678.0800085003}}, {"cid": "QmWWDtAJTuxfUeujBrM62NNd4SFWs97S3YYYcBeHeeYuKU", "dur": 11, "ts": 1636758391.141, "upload_date": "2021-11-12", "category": "new", "local_check_ts": null, "public_check_ts": 1637296587.0080035, "local_data": null, "public_data": {"overhead": 0.240796, "download_time": 1.04836, "file_size": 1672441.0, "video_length": 11, "stall_rate": 0, "bandwidth": 1595292.647563814}}, {"cid": "QmdzT3ZVc4FEemaJAksZHMsHr16Y22xSCJhGTLPM9kcPZB", "dur": 210, "ts": 1636747266.055, "upload_date": "2021-11-12", "category": "new", "local_check_ts": null, "public_check_ts": 1637296741.2318246, "local_data": null, "public_data": {"overhead": 0.457436, "download_time": 32.879866, "file_size": 30403303.0, "video_length": 210, "stall_rate": 0, "bandwidth": 924678.4339084594}}, {"cid": "QmYvGnsZrrWap8hRy7iDPzgtcbHJXjpRdt6EUms8hsT7cB", "dur": 17, "ts": 1636739336.886, "upload_date": "2021-11-12", "category": "new", "local_check_ts": null, "public_check_ts": 1637296865.4375129, "local_data": null, "public_data": {"overhead": 0.414205, "download_time": 2.930318, "file_size": 2493220.0, "video_length": 17, "stall_rate": 0, "bandwidth": 850835.9843539165}}, {"cid": "QmQLye1RdtoQ5xrhPGbrJUd1nsPuvC9rbjSbGCDtLz8b4Z", "dur": 4, "ts": 1636738524.338, "upload_date": "2021-11-12", "category": "new", "local_check_ts": null, "public_check_ts": 1637296986.827829, "local_data": null, "public_data": {"overhead": 0.393788, "download_time": 0.16864599999999996, "file_size": 133005.0, "video_length": 4, "stall_rate": 0, "bandwidth": 788663.8283742279}}, {"cid": "QmQs85UvKpeHu9cvsheiTekX3MucJnWvEgf8AvtyRdaxsh", "dur": 401, "ts": 1636738152.817, "upload_date": "2021-11-12", "category": "new", "local_check_ts": null, "public_check_ts": 1637297122.8588707, "local_data": null, "public_data": {"overhead": 1.767948, "download_time": 13.649172, "file_size": 23023380.0, "video_length": 401, "stall_rate": 0, "bandwidth": 1686796.8254777652}}, {"cid": "Qmf53sAmpiTUQtbB88DcB2Wh5JEGJrR1y5ZoynMJb4HRY4", "dur": 463, "ts": 1636736545.829, "upload_date": "2021-11-12", "category": "new", "local_check_ts": null, "public_check_ts": 1637297363.626276, "local_data": null, "public_data": {"overhead": 0.453543, "download_time": 119.538233, "file_size": 67773548.0, "video_length": 463, "stall_rate": 0, "bandwidth": 566961.2666936443}}, {"cid": "QmZmaJDpbN6veprm96o3psQ1KQSTiHq7RYRm6u8SZEFbkA", "dur": 255, "ts": 1636715059.821, "upload_date": "2021-11-12", "category": "hot", "local_check_ts": null, "public_check_ts": 1637297589.2672799, "local_data": null, "public_data": {"overhead": 7.850368, "download_time": 97.463991, "file_size": 54378371.0, "video_length": 255, "stall_rate": 0, "bandwidth": 557932.9395612376}}, {"cid": "QmNoG7AxDXCes1ioZfFw5z2cnqai6BuvF87j1YnLXL6E3Q", "dur": 426, "ts": 1636778064.73, "upload_date": "2021-11-13", "category": "trending", "local_check_ts": 1637297662.3638132, "public_check_ts": 1637297662.7998037, "local_data": {"overhead": 2.240397, "download_time": 70.02539399999999, "file_size": 274389922.0, "video_length": 426, "stall_rate": 0, "bandwidth": 3918434.532478318}, "public_data": {"overhead": 0.303839, "download_time": 0.0005239999999999689, "file_size": 169.0, "video_length": 426, "stall_rate": 0, "bandwidth": 322519.0839694848}}, {"cid": "QmP5RhQwE3sZkgbDRyHMqXxt91SqysyJYwcCE2XMUDe2oZ", "dur": 1457, "ts": 1636762997.764, "upload_date": "2021-11-13", "category": "trending", "local_check_ts": null, "public_check_ts": "", "local_data": null, "public_data": null}, {"cid": "QmQeS82TUXgYbVQQgNCRJj6XbU8KDHEe1VECACtkpH5M62", "dur": 59, "ts": 1636814895.487, "upload_date": "2021-11-13", "category": "trending", "local_check_ts": null, "public_check_ts": 1637298034.4500687, "local_data": null, "public_data": {"overhead": 0.372975, "download_time": 4.775004, "file_size": 8902185.0, "video_length": 59, "stall_rate": 0, "bandwidth": 1864330.375430052}}, {"cid": "QmSqX6iCke3LEaGoEj5aiHJ4ZH5P8ZjhyKvi1J4r5Wumxt", "dur": 36, "ts": 1636775760.011, "upload_date": "2021-11-13", "category": "trending", "local_check_ts": null, "public_check_ts": 1637298160.1147594, "local_data": null, "public_data": {"overhead": 0.418753, "download_time": 4.221316000000001, "file_size": 5165136.0, "video_length": 36, "stall_rate": 0, "bandwidth": 1223584.3040416779}}, {"cid": "QmRNb752NYqDVJakNBuZJYhXsX7oqNsnVfyLs19KEqjyfn", "dur": 60, "ts": 1636815991.979, "upload_date": "2021-11-13", "category": "trending", "local_check_ts": null, "public_check_ts": 1637298286.9978247, "local_data": null, "public_data": {"overhead": 0.503551, "download_time": 5.739543, "file_size": 9004265.0, "video_length": 60, "stall_rate": 0, "bandwidth": 1568812.185917938}}, {"cid": "QmVgTDwCxmSVVLyxH9yjk8yfgGxP9pACHgJM5QEMbGF7uQ", "dur": 784, "ts": 1636800774.123, "upload_date": "2021-11-13", "category": "trending", "local_check_ts": null, "public_check_ts": 1637298449.0511339, "local_data": null, "public_data": {"overhead": 0.576444, "download_time": 40.539944, "file_size": 114151173.0, "video_length": 784, "stall_rate": 0, "bandwidth": 2815770.3671223624}}, {"cid": "QmZ3wgRvfYQWzUWLZuRR79yioCJzfuajA822JjF76imEG7", "dur": 57, "ts": 1636816158.109, "upload_date": "2021-11-13", "category": "trending", "local_check_ts": null, "public_check_ts": 1637298571.4396472, "local_data": null, "public_data": {"overhead": 0.289523, "download_time": 0.999736, "file_size": 8140469.0, "video_length": 57, "stall_rate": 0, "bandwidth": 8142618.65132395}}, {"cid": "QmY8noYf5dTjdzLqAPK2BAMqJxy2Kj5p49wJbxxFticDGD", "dur": 410, "ts": 1636846829.968, "upload_date": "2021-11-13", "category": "new", "local_check_ts": null, "public_check_ts": 1637298700.4603546, "local_data": null, "public_data": {"overhead": 0.22842, "download_time": 7.896928000000001, "file_size": 18713389.0, "video_length": 410, "stall_rate": 0, "bandwidth": 2369704.9029698633}}, {"cid": "Qmb4kyzUH7tQVtk1k9DNTabvz3KbbCr5E6XHRVogbxi5YY", "dur": 7466, "ts": 1636844766.891, "upload_date": "2021-11-13", "category": "new", "local_check_ts": null, "public_check_ts": "", "local_data": null, "public_data": null}, {"cid": "QmaS4aRGbDqaoeBJebssygMGVHX87TKzufVzUrNTM77K2G", "dur": 294, "ts": 1636839420.265, "upload_date": "2021-11-13", "category": "new", "local_check_ts": null, "public_check_ts": 1637299162.5016482, "local_data": null, "public_data": {"overhead": 0.504883, "download_time": 3.263569, "file_size": 41957603.0, "video_length": 294, "stall_rate": 0, "bandwidth": 12856355.419480942}}, {"cid": "QmSEFTGgibsjzFZCviCL5TFqfDrPiyZJhfJTXV6zXXNGfM", "dur": 299, "ts": 1636832046.931, "upload_date": "2021-11-13", "category": "new", "local_check_ts": null, "public_check_ts": 1637299285.608071, "local_data": null, "public_data": {"overhead": 0.199945, "download_time": 2.288259, "file_size": 41448752.0, "video_length": 299, "stall_rate": 0, "bandwidth": 18113662.832747515}}, {"cid": "Qmez22a9mr3HCVa8BpjUSxEEZFCqMh91BxpDjd4p5aUvNt", "dur": 190, "ts": 1636829576.082, "upload_date": "2021-11-13", "category": "new", "local_check_ts": null, "public_check_ts": 1637299408.3846889, "local_data": null, "public_data": {"overhead": 1.101351, "download_time": 1.385098, "file_size": 29542831.0, "video_length": 190, "stall_rate": 0, "bandwidth": 21329054.69504685}}, {"cid": "QmNMs85AyRRPReGnLTsLYN5LGVT2oTGbP6sC7sUCc7voCp", "dur": 175, "ts": 1636821456.305, "upload_date": "2021-11-13", "category": "new", "local_check_ts": null, "public_check_ts": 1637299530.271074, "local_data": null, "public_data": {"overhead": 0.187561, "download_time": 0.5089670000000001, "file_size": 9288802.0, "video_length": 175, "stall_rate": 0, "bandwidth": 18250303.064835243}}, {"cid": "QmQYtFQttURc8VxytEMCx6kkZwiWKSFKCa1XC3KCmsMuZR", "dur": 2, "ts": 1636818574.612, "upload_date": "2021-11-13", "category": "new", "local_check_ts": null, "public_check_ts": 1637299660.0908544, "local_data": null, "public_data": {"overhead": 1.82925, "download_time": 7.52731, "file_size": 17121565.0, "video_length": 2, "stall_rate": 2.763655, "bandwidth": 2274592.782813515}}, {"cid": "QmSvf7CGjGGmSei7rR8yFvWuBnAzy7kBbr4tTqqmia58MQ", "dur": 420, "ts": 1636812702.568, "upload_date": "2021-11-13", "category": "new", "local_check_ts": null, "public_check_ts": 1637299824.349427, "local_data": null, "public_data": {"overhead": 0.759588, "download_time": 42.689589, "file_size": 61103242.0, "video_length": 420, "stall_rate": 0, "bandwidth": 1431338.2590776407}}, {"cid": "Qmeiep545n3ZcHb7qQgaZfPRC2EHa2YKWmXzze4fkGq8Au", "dur": 49, "ts": 1636809981.013, "upload_date": "2021-11-13", "category": "hot", "local_check_ts": null, "public_check_ts": 1637299949.566697, "local_data": null, "public_data": {"overhead": 0.334475, "download_time": 3.9858170000000004, "file_size": 35132307.0, "video_length": 49, "stall_rate": 0, "bandwidth": 8814330.161168965}}, {"cid": "Qmbp9uJYySUqsA9c9D521A8T5NKHAyqgxqSscsUxQuZiHv", "dur": 319, "ts": 1636799366.419, "upload_date": "2021-11-13", "category": "hot", "local_check_ts": null, "public_check_ts": 1637300074.6597102, "local_data": null, "public_data": {"overhead": 0.457531, "download_time": 3.5630859999999998, "file_size": 46865690.0, "video_length": 319, "stall_rate": 0, "bandwidth": 13153117.8310038}}, {"cid": "QmTQoFJovsZD8afouiRodtpMiDxYfh88tHCJrhafYVwg8f", "dur": 398, "ts": 1636776787.02, "upload_date": "2021-11-13", "category": "hot", "local_check_ts": null, "public_check_ts": 1637300204.256627, "local_data": null, "public_data": {"overhead": 0.303586, "download_time": 8.862710000000002, "file_size": 83311339.0, "video_length": 398, "stall_rate": 0, "bandwidth": 9400210.432249276}}, {"cid": "QmcHA9Ms1awkMmz8WUemtRiYuEHKUzkZeSLQ9HAEm54Rwy", "dur": 43, "ts": 1636803960.872, "upload_date": "2021-11-13", "category": "hot", "local_check_ts": null, "public_check_ts": 1637300325.4451532, "local_data": null, "public_data": {"overhead": 0.253757, "download_time": 0.500665, "file_size": 6460086.0, "video_length": 43, "stall_rate": 0, "bandwidth": 12903010.99537615}}, {"cid": "QmWuERqJXtFHnUaBu5TVLLxKdtJBA769B89v3YtAAuPXF7", "dur": 16, "ts": 1636879603.95, "upload_date": "2021-11-14", "category": "trending", "local_check_ts": null, "public_check_ts": 1637300446.382969, "local_data": null, "public_data": {"overhead": 0.330262, "download_time": 0.19356800000000002, "file_size": 2521675.0, "video_length": 16, "stall_rate": 0, "bandwidth": 13027334.063481566}}, {"cid": "QmbijsKFw2568acaF85QWzrvzkQNeM6e7UVWWGb1w7g2Gm", "dur": 130, "ts": 1636904705.523, "upload_date": "2021-11-14", "category": "trending", "local_check_ts": null, "public_check_ts": 1637300568.4232714, "local_data": null, "public_data": {"overhead": 0.311988, "download_time": 1.056481, "file_size": 19560612.0, "video_length": 130, "stall_rate": 0, "bandwidth": 18514873.433597006}}, {"cid": "QmWsG8JwarHQoQJnLNrXSX2GGD4unbnSwoMaVdn8voWzkq", "dur": 329, "ts": 1636931266.458, "upload_date": "2021-11-14", "category": "new", "local_check_ts": null, "public_check_ts": 1637300691.240222, "local_data": null, "public_data": {"overhead": 0.2453, "download_time": 2.376526, "file_size": 48050462.0, "video_length": 329, "stall_rate": 0, "bandwidth": 20218782.373935737}}, {"cid": "QmQYzBGpXVcAkLmewtv58Ab1SA52yN5gnMAqVg3RKPzZCo", "dur": 20, "ts": 1636925856.464, "upload_date": "2021-11-14", "category": "new", "local_check_ts": null, "public_check_ts": 1637300812.362201, "local_data": null, "public_data": {"overhead": 0.346385, "download_time": 0.012776999999999983, "file_size": 94132.0, "video_length": 20, "stall_rate": 0, "bandwidth": 7367300.618298515}}, {"cid": "QmdA41wtqTErn9qGdxGErq2qi4ctaXnJ7oUme3XiLk9hsM", "dur": 2740, "ts": 1636925774.91, "upload_date": "2021-11-14", "category": "new", "local_check_ts": null, "public_check_ts": 1637300993.8479202, "local_data": null, "public_data": {"overhead": 0.519668, "download_time": 60.125941, "file_size": 321791523.0, "video_length": 2740, "stall_rate": 0, "bandwidth": 5351958.200537768}}, {"cid": "QmZiGs4p9W3zdqvrq5rvhQL4tFiAPfpvCdxAgTSzhdxRnR", "dur": 11080, "ts": 1636925539.285, "upload_date": "2021-11-14", "category": "new", "local_check_ts": null, "public_check_ts": 1637301115.0186374, "local_data": null, "public_data": {"overhead": 0.363449, "download_time": 0.0017009999999999525, "file_size": 169.0, "video_length": 11080, "stall_rate": 0, "bandwidth": 99353.32157554656}}, {"cid": "QmPkb8iwC93c2eDYmaprq8FdwXRrs23GvNHw3MHGFHaebL", "dur": 130, "ts": 1636922165.115, "upload_date": "2021-11-14", "category": "new", "local_check_ts": null, "public_check_ts": 1637301285.461714, "local_data": null, "public_data": {"overhead": 22.320993, "download_time": 27.120297, "file_size": 17520002.0, "video_length": 130, "stall_rate": 0, "bandwidth": 646010.6981866754}}, {"cid": "QmNgXr1gpyMDKuYf1nhWPybzT61oZheqBtAHveCDHCTnZD", "dur": 629, "ts": 1636915930.425, "upload_date": "2021-11-14", "category": "new", "local_check_ts": null, "public_check_ts": 1637301414.3694627, "local_data": null, "public_data": {"overhead": 0.464186, "download_time": 7.661541, "file_size": 91577029.0, "video_length": 629, "stall_rate": 0, "bandwidth": 11952821.11000907}}, {"cid": "QmSDuDzgaQyCKHW2zTsYLDSHE3nmpTcU48BK8aBW7VqZ3V", "dur": 79, "ts": 1636915631.291, "upload_date": "2021-11-14", "category": "new", "local_check_ts": null, "public_check_ts": 1637301537.1119788, "local_data": null, "public_data": {"overhead": 0.567737, "download_time": 1.2832569999999999, "file_size": 11713563.0, "video_length": 79, "stall_rate": 0, "bandwidth": 9127994.626173869}}, {"cid": "QmZZa1bXjYN819E7dvnWCiqZShpkPZVgW5c99PFhB5J8XB", "dur": 2559, "ts": 1636915302.031, "upload_date": "2021-11-14", "category": "new", "local_check_ts": null, "public_check_ts": 1637301696.9652507, "local_data": null, "public_data": {"overhead": 0.684084, "download_time": 38.833939, "file_size": 452385420.0, "video_length": 2559, "stall_rate": 0, "bandwidth": 11649228.269117897}}, {"cid": "Qmc9Vg3FJdEA6w2pMzqbwp6eLq24MzXA3HGbKMMTHhaNuE", "dur": 236, "ts": 1636913728.301, "upload_date": "2021-11-14", "category": "new", "local_check_ts": null, "public_check_ts": 1637301820.1628022, "local_data": null, "public_data": {"overhead": 0.2518, "download_time": 1.9398060000000001, "file_size": 30814555.0, "video_length": 236, "stall_rate": 0, "bandwidth": 15885379.77509091}}, {"cid": "QmQ2wBp7sDr52oLGbLjtsaQmJ1PPK4pJ2NmACHi3Mujzoh", "dur": 736, "ts": 1636910308.938, "upload_date": "2021-11-14", "category": "hot", "local_check_ts": null, "public_check_ts": 1637301940.754685, "local_data": null, "public_data": {"overhead": 0.285682, "download_time": 0.0005999999999999894, "file_size": 169.0, "video_length": 736, "stall_rate": 0, "bandwidth": 281666.66666667163}}, {"cid": "QmZ5o1887KPDndPh13DapGogqyD55wJG7LRii8C5AzZexr", "dur": 3738, "ts": 1636910009.883, "upload_date": "2021-11-14", "category": "hot", "local_check_ts": null, "public_check_ts": 1637302061.9622178, "local_data": null, "public_data": {"overhead": 0.293961, "download_time": 0.0007400000000000184, "file_size": 169.0, "video_length": 3738, "stall_rate": 0, "bandwidth": 228378.3783783727}}, {"cid": "QmdiQt6L5ZvnQ1vfdrhzTr7Rhn8wCJSCsBJ45jW2uWumh4", "dur": 325, "ts": 1636888303.35, "upload_date": "2021-11-14", "category": "hot", "local_check_ts": null, "public_check_ts": 1637302232.871527, "local_data": null, "public_data": {"overhead": 0.710854, "download_time": 49.292316, "file_size": 45751394.0, "video_length": 325, "stall_rate": 0, "bandwidth": 928164.8279622325}}, {"cid": "Qmba9n19FZ5FusRvofhgP5PnR6DiMxUjc6SEoZgW64aYEw", "dur": 843, "ts": 1637014370.745, "upload_date": "2021-11-15", "category": "trending", "local_check_ts": null, "public_check_ts": 1637302359.0630028, "local_data": null, "public_data": {"overhead": 0.32274, "download_time": 5.501696000000001, "file_size": 84385973.0, "video_length": 843, "stall_rate": 0, "bandwidth": 15338174.446570655}}, {"cid": "Qmc7Tazt6kZzspxNCzb5NJ42hjTYEezhxFQ7AEena4YsYL", "dur": 60, "ts": 1636991310.931, "upload_date": "2021-11-15", "category": "trending", "local_check_ts": null, "public_check_ts": 1637302481.0327032, "local_data": null, "public_data": {"overhead": 0.308854, "download_time": 0.5887849999999999, "file_size": 8783895.0, "video_length": 60, "stall_rate": 0, "bandwidth": 14918679.993546033}}, {"cid": "QmZSR5omdUfCRfwVG4g9PkxMsbwMPjqFBD7gBHEGRXeVeV", "dur": 463, "ts": 1636954444.082, "upload_date": "2021-11-15", "category": "trending", "local_check_ts": null, "public_check_ts": 1637302601.5083313, "local_data": null, "public_data": {"overhead": 0.198063, "download_time": 0.0005860000000000032, "file_size": 169.0, "video_length": 463, "stall_rate": 0, "bandwidth": 288395.9044368585}}, {"cid": "QmXkbcXNkQRi4as6szfCCAJXebjS6Dv7HkxwUsPcFVbBZa", "dur": 82, "ts": 1637011516.25, "upload_date": "2021-11-15", "category": "trending", "local_check_ts": null, "public_check_ts": 1637302725.8729732, "local_data": null, "public_data": {"overhead": 0.263495, "download_time": 3.0905820000000004, "file_size": 14750656.0, "video_length": 82, "stall_rate": 0, "bandwidth": 4772776.130838786}}, {"cid": "QmWqQMeuoDaasKVoDKjGNMSxvQHwMnK4MSaNNhS2Bsf7Dg", "dur": 42, "ts": 1636961233.614, "upload_date": "2021-11-15", "category": "trending", "local_check_ts": null, "public_check_ts": 1637302847.8659873, "local_data": null, "public_data": {"overhead": 0.785566, "download_time": 0.3752200000000001, "file_size": 6570116.0, "video_length": 42, "stall_rate": 0, "bandwidth": 17510036.77842332}}, {"cid": "Qme2RZsK3TcNPHf6NJuUvXK2zvxykxQ9Az7Bg5Sob6swBm", "dur": 118, "ts": 1636966565.29, "upload_date": "2021-11-15", "category": "trending", "local_check_ts": null, "public_check_ts": 1637302969.9538007, "local_data": null, "public_data": {"overhead": 0.137895, "download_time": 0.909398, "file_size": 16594087.0, "video_length": 118, "stall_rate": 0, "bandwidth": 18247331.7513344}}, {"cid": "QmXCRovmPFAV1Zakc4aDVr2kzAtrMpEXzJV8NfM8Dxc7QQ", "dur": 60, "ts": 1636955229.143, "upload_date": "2021-11-15", "category": "trending", "local_check_ts": null, "public_check_ts": 1637303091.8808267, "local_data": null, "public_data": {"overhead": 0.583237, "download_time": 1.09473, "file_size": 8659220.0, "video_length": 60, "stall_rate": 0, "bandwidth": 7909913.860038549}}, {"cid": "Qmc6PXQyUtpu1HnaT9qGNQJEK3EubYNAFCEHxo7LNkeJHE", "dur": 60, "ts": 1637015252.817, "upload_date": "2021-11-15", "category": "new", "local_check_ts": null, "public_check_ts": 1637303233.3762243, "local_data": null, "public_data": {"overhead": 6.097585, "download_time": 14.883726000000003, "file_size": 5594084.0, "video_length": 60, "stall_rate": 0, "bandwidth": 375852.39072527934}}, {"cid": "QmScLiCUNdPaHbCV6SreLkKbFVaZfHdbyxPMQRJaZL1NfR", "dur": 171, "ts": 1637013102.069, "upload_date": "2021-11-15", "category": "new", "local_check_ts": null, "public_check_ts": 1637303355.8863797, "local_data": null, "public_data": {"overhead": 0.198411, "download_time": 1.8766249999999998, "file_size": 28433442.0, "video_length": 171, "stall_rate": 0, "bandwidth": 15151371.2116166}}, {"cid": "QmbqL47vdJNKui21n6UNZfWHh6uB9srkpit1uRnUUdvzY6", "dur": 12, "ts": 1637012766.775, "upload_date": "2021-11-15", "category": "new", "local_check_ts": null, "public_check_ts": 1637303477.5201035, "local_data": null, "public_data": {"overhead": 0.248963, "download_time": 0.17201900000000003, "file_size": 1724374.0, "video_length": 12, "stall_rate": 0, "bandwidth": 10024322.894563971}}, {"cid": "QmWe6DzvfMwp3aZtXhC4ZJpABtSbvjbyT1kD5tNwMErnKw", "dur": 855, "ts": 1637012084.111, "upload_date": "2021-11-15", "category": "new", "local_check_ts": null, "public_check_ts": 1637303605.2576873, "local_data": null, "public_data": {"overhead": 0.189628, "download_time": 6.7969100000000005, "file_size": 123656919.0, "video_length": 855, "stall_rate": 0, "bandwidth": 18193108.19181069}}, {"cid": "QmXeBYGjyK5wjbcs2v1fptiEUMH1Dx4WLtPqHY82pyLqLZ", "dur": 1, "ts": 1637011464.899, "upload_date": "2021-11-15", "category": "new", "local_check_ts": null, "public_check_ts": 1637303726.236329, "local_data": null, "public_data": {"overhead": 0.363393, "download_time": 0.10145299999999996, "file_size": 959802.0, "video_length": 1, "stall_rate": 0, "bandwidth": 9460558.090938665}}, {"cid": "QmeGSo5LTruxiBqLVJar9Ggsvc1b3NhC2osNWw5WRAaKbh", "dur": 1194, "ts": 1637011057.094, "upload_date": "2021-11-15", "category": "new", "local_check_ts": null, "public_check_ts": 1637303857.091234, "local_data": null, "public_data": {"overhead": 0.292925, "download_time": 9.835352, "file_size": 174658810.0, "video_length": 1194, "stall_rate": 0, "bandwidth": 17758267.31976649}}, {"cid": "QmVGXiM2vpvdvjiPjSW54Pir8VE3YVoht8UyaY7XPHhmAz", "dur": 248, "ts": 1637009824.681, "upload_date": "2021-11-15", "category": "new", "local_check_ts": null, "public_check_ts": 1637303978.9000733, "local_data": null, "public_data": {"overhead": 0.137619, "download_time": 1.413764, "file_size": 22659892.0, "video_length": 248, "stall_rate": 0, "bandwidth": 16028058.43125161}}, {"cid": "QmWg44q1e2HCtVF7ccYyWzrzjEHqzf9d51KX42dkfu348z", "dur": 520, "ts": 1637009721.987, "upload_date": "2021-11-15", "category": "new", "local_check_ts": null, "public_check_ts": 1637304103.8087032, "local_data": null, "public_data": {"overhead": 0.148823, "download_time": 4.100447, "file_size": 74584980.0, "video_length": 520, "stall_rate": 0, "bandwidth": 18189475.44011665}}, {"cid": "QmdVsbix5oGMRcK5QZxmM7if8BBpK1YRTVBTDMwaWuxFqp", "dur": 1440, "ts": 1637009202.432, "upload_date": "2021-11-15", "category": "new", "local_check_ts": null, "public_check_ts": 1637304245.932993, "local_data": null, "public_data": {"overhead": 0.160333, "download_time": 21.025959, "file_size": 376504132.0, "video_length": 1440, "stall_rate": 0, "bandwidth": 17906633.033955786}}, {"cid": "QmWe1C17M3rc6H71gpah3SHxqvDjTcXyg796f5pwSe2ELN", "dur": 60, "ts": 1637007154.362, "upload_date": "2021-11-15", "category": "new", "local_check_ts": null, "public_check_ts": 1637304367.2107692, "local_data": null, "public_data": {"overhead": 0.136754, "download_time": 0.10295200000000002, "file_size": 1662809.0, "video_length": 60, "stall_rate": 0, "bandwidth": 16151303.520087028}}, {"cid": "QmNiVBQydHnDdadAHYkNaJaeahkcNwABaSjxowT74VYUuw", "dur": 324, "ts": 1637003605.049, "upload_date": "2021-11-15", "category": "new", "local_check_ts": null, "public_check_ts": 1637304500.8257165, "local_data": null, "public_data": {"overhead": 0.137833, "download_time": 12.549529999999999, "file_size": 214807045.0, "video_length": 324, "stall_rate": 0, "bandwidth": 17116740.22851852}}, {"cid": "QmYtumE2mXhoVNtw7Lr6o5VA3rS1S8v4PW1qxL9b27T48S", "dur": 4025, "ts": 1637003269.755, "upload_date": "2021-11-15", "category": "new", "local_check_ts": null, "public_check_ts": 1637304633.7151077, "local_data": null, "public_data": {"overhead": 0.172103, "download_time": 11.518361, "file_size": 200440966.0, "video_length": 4025, "stall_rate": 0, "bandwidth": 17401865.248015754}}, {"cid": "QmRUwhDncKW6LPGwSzS845hribq58sCv67nJ6UjMDEQ5YQ", "dur": 278, "ts": 1637080709.114, "upload_date": "2021-11-16", "category": "trending", "local_check_ts": null, "public_check_ts": 1637304757.225866, "local_data": null, "public_data": {"overhead": 0.225691, "download_time": 2.265194, "file_size": 37724181.0, "video_length": 278, "stall_rate": 0, "bandwidth": 16653841.127956368}}, {"cid": "QmQQGZ89Vt6XZBSpE9xFUiM4nYMDgtzXJx7b3dpfpSBg4q", "dur": 97, "ts": 1637038376.237, "upload_date": "2021-11-16", "category": "trending", "local_check_ts": null, "public_check_ts": 1637304879.073506, "local_data": null, "public_data": {"overhead": 0.154203, "download_time": 0.790663, "file_size": 13061907.0, "video_length": 97, "stall_rate": 0, "bandwidth": 16520195.076789984}}, {"cid": "QmYsamAWgD5jqc4HxxwTNerhuM5NUXiKTxijnyyEM7FEzY", "dur": 66, "ts": 1637033340.635, "upload_date": "2021-11-16", "category": "trending", "local_check_ts": null, "public_check_ts": 1637305000.212973, "local_data": null, "public_data": {"overhead": 0.21919, "download_time": 0.678725, "file_size": 8901088.0, "video_length": 66, "stall_rate": 0, "bandwidth": 13114424.840693947}}, {"cid": "QmfTADijfSQux8x2Jkc7sNC7cmSpAiXjyzSvzqcHhP5AG7", "dur": 11, "ts": 1637060539.697, "upload_date": "2021-11-16", "category": "trending", "local_check_ts": null, "public_check_ts": 1637305131.0118, "local_data": null, "public_data": {"overhead": 4.722075, "download_time": 5.799118, "file_size": 1643977.0, "video_length": 11, "stall_rate": 0, "bandwidth": 283487.4199835216}}, {"cid": "QmbrnxKC7JxHWACTEJmhAJgcnzTza6z1KUSnyMiRVTBWnx", "dur": 26, "ts": 1637027127.026, "upload_date": "2021-11-16", "category": "trending", "local_check_ts": null, "public_check_ts": 1637305252.4363613, "local_data": null, "public_data": {"overhead": 0.485385, "download_time": 0.246608, "file_size": 3796580.0, "video_length": 26, "stall_rate": 0, "bandwidth": 15395202.102121586}}, {"cid": "QmQRAo7g3X2pNpE3NdFfRQF41oGfAHeL9mYBfUe4pNqYyX", "dur": 245, "ts": 1637104367.284, "upload_date": "2021-11-16", "category": "trending", "local_check_ts": null, "public_check_ts": 1637305376.9139123, "local_data": null, "public_data": {"overhead": 0.436775, "download_time": 3.599436, "file_size": 33817917.0, "video_length": 245, "stall_rate": 0, "bandwidth": 9395337.769583901}}, {"cid": "Qmdk2eBnVYfNjLnGCzKyTn5vTrXCpfPszHzY1uqopRrPyj", "dur": 652, "ts": 1637104889.875, "upload_date": "2021-11-16", "category": "new", "local_check_ts": null, "public_check_ts": 1637305506.904306, "local_data": null, "public_data": {"overhead": 0.146831, "download_time": 9.38947, "file_size": 175714677.0, "video_length": 652, "stall_rate": 0, "bandwidth": 18714014.422539294}}, {"cid": "QmPUZP8Z3Erra5UFQnv8dMRmEthxhPeqAG98aEVuektSxG", "dur": 860, "ts": 1637104258.547, "upload_date": "2021-11-16", "category": "new", "local_check_ts": null, "public_check_ts": 1637305643.5459173, "local_data": null, "public_data": {"overhead": 0.162821, "download_time": 15.815304000000001, "file_size": 299524998.0, "video_length": 860, "stall_rate": 0, "bandwidth": 18938933.959157534}}, {"cid": "QmW9m45ks2zfHWxNLGhPW15AEjTkDbJKyxH97CReUMPeVX", "dur": 1462, "ts": 1637103732.956, "upload_date": "2021-11-16", "category": "new", "local_check_ts": null, "public_check_ts": 1637305790.0794568, "local_data": null, "public_data": {"overhead": 0.140017, "download_time": 25.753052, "file_size": 387161150.0, "video_length": 1462, "stall_rate": 0, "bandwidth": 15033602.619215773}}, {"cid": "QmSSLaA9HH56415pvZ17GHW3eyyRpNURbLYkPsyvY1yTg5", "dur": 211, "ts": 1637102128.902, "upload_date": "2021-11-16", "category": "new", "local_check_ts": null, "public_check_ts": 1637305913.9430153, "local_data": null, "public_data": {"overhead": 0.165979, "download_time": 2.470593, "file_size": 43665692.0, "video_length": 211, "stall_rate": 0, "bandwidth": 17674174.580758546}}, {"cid": "QmNb2VYfiE8aadivLCDin7YHXDyyZKBGb1tp7qQ5foWQYv", "dur": 215, "ts": 1637101255.932, "upload_date": "2021-11-16", "category": "new", "local_check_ts": null, "public_check_ts": 1637306036.680929, "local_data": null, "public_data": {"overhead": 0.129886, "download_time": 1.743879, "file_size": 31374474.0, "video_length": 215, "stall_rate": 0, "bandwidth": 17991198.930659752}}, {"cid": "QmRvU31SyZtQ3NFr5MXjCVQdruuJZULNHrZRxHUiUWYH5y", "dur": 258, "ts": 1637100908.559, "upload_date": "2021-11-16", "category": "new", "local_check_ts": null, "public_check_ts": 1637306161.1496034, "local_data": null, "public_data": {"overhead": 0.900981, "download_time": 3.253114, "file_size": 37424580.0, "video_length": 258, "stall_rate": 0, "bandwidth": 11504232.55994103}}, {"cid": "Qme5dJmSpb4bDyBjWQXSH5MTCEzd7oSdPoejBGTKX5QUwR", "dur": 1065, "ts": 1637100349.744, "upload_date": "2021-11-16", "category": "new", "local_check_ts": null, "public_check_ts": 1637306295.8737297, "local_data": null, "public_data": {"overhead": 0.590763, "download_time": 13.095766999999999, "file_size": 158701000.0, "video_length": 1065, "stall_rate": 0, "bandwidth": 12118495.99950885}}, {"cid": "QmRnBYYmCaHN2WVuXbHYHYK2JT67SUSK4Us1gvwjw7SPpd", "dur": 18, "ts": 1637099292.542, "upload_date": "2021-11-16", "category": "new", "local_check_ts": null, "public_check_ts": 1637306417.4492288, "local_data": null, "public_data": {"overhead": 0.22417, "download_time": 0.148251, "file_size": 2394770.0, "video_length": 18, "stall_rate": 0, "bandwidth": 16153482.944465805}}, {"cid": "QmUPfMkSLzPzkFm4zGxcWSbqJg3UJSAa7MtPzef5GgvcwJ", "dur": 297, "ts": 1637098739.748, "upload_date": "2021-11-16", "category": "new", "local_check_ts": null, "public_check_ts": 1637306541.1940398, "local_data": null, "public_data": {"overhead": 0.321087, "download_time": 2.5965380000000002, "file_size": 43581856.0, "video_length": 297, "stall_rate": 0, "bandwidth": 16784601.65035135}}, {"cid": "QmQ6MwpQhVCe64u91fHmetK9kFgzVXyS55kFukXTP2qDht", "dur": 21, "ts": 1637098594.76, "upload_date": "2021-11-16", "category": "new", "local_check_ts": null, "public_check_ts": 1637306662.0634007, "local_data": null, "public_data": {"overhead": 0.106708, "download_time": 0.18977000000000002, "file_size": 3339016.0, "video_length": 21, "stall_rate": 0, "bandwidth": 17595067.71354798}}, {"cid": "QmR3o6XVLvaz6Rg4xTHhLeCdzpSoxr1KKnQBpnWziPjN1y", "dur": 245, "ts": 1637098017.814, "upload_date": "2021-11-16", "category": "new", "local_check_ts": null, "public_check_ts": 1637306791.9572403, "local_data": null, "public_data": {"overhead": 2.206339, "download_time": 6.795769, "file_size": 35549270.0, "video_length": 245, "stall_rate": 0, "bandwidth": 5231088.637650868}}, {"cid": "QmUSx21mbHXd43MfxWfoQcD1X7QLqPyrvP7Jbrt6tEeW8k", "dur": 293, "ts": 1637096872.99, "upload_date": "2021-11-16", "category": "new", "local_check_ts": null, "public_check_ts": 1637306916.7054353, "local_data": null, "public_data": {"overhead": 1.421435, "download_time": 3.037051, "file_size": 42684718.0, "video_length": 293, "stall_rate": 0, "bandwidth": 14054659.602357682}}, {"cid": "QmUBogHuAp96Pcyb8vyhPVCpDN9DedfHBc6G8PBwbjPXBp", "dur": 113, "ts": 1637096788.409, "upload_date": "2021-11-16", "category": "new", "local_check_ts": null, "public_check_ts": 1637307038.2779791, "local_data": null, "public_data": {"overhead": 0.225548, "download_time": 0.210572, "file_size": 3573659.0, "video_length": 113, "stall_rate": 0, "bandwidth": 16971197.50014247}}, {"cid": "QmeZherbzZfL5kZqaCwk8VkZUbkxByEEhyQ4jqDJ8i8N8f", "dur": 123, "ts": 1637093024.649, "upload_date": "2021-11-16", "category": "new", "local_check_ts": null, "public_check_ts": 1637307160.1671314, "local_data": null, "public_data": {"overhead": 0.269989, "download_time": 0.8615489999999999, "file_size": 16543554.0, "video_length": 123, "stall_rate": 0, "bandwidth": 19202104.581399318}}, {"cid": "QmRb6U1pV8LtxBcsCwvyymrvypvUVdpUqYHQQHR4kq7era", "dur": 399, "ts": 1637089774.433, "upload_date": "2021-11-16", "category": "new", "local_check_ts": null, "public_check_ts": 1637307283.9235783, "local_data": null, "public_data": {"overhead": 0.337372, "download_time": 3.1702589999999997, "file_size": 58499411.0, "video_length": 399, "stall_rate": 0, "bandwidth": 18452565.23205202}}, {"cid": "QmQqfi2YuhLXgzPUGUpgrw3WyUdKybBDP5FGUySMzpR5xB", "dur": 1153, "ts": 1637089001.143, "upload_date": "2021-11-16", "category": "new", "local_check_ts": null, "public_check_ts": 1637307414.6121557, "local_data": null, "public_data": {"overhead": 0.175033, "download_time": 9.729654, "file_size": 170935837.0, "video_length": 1153, "stall_rate": 0, "bandwidth": 17568542.211264655}}, {"cid": "QmPQRgZLpNyxRUitFfch3yznASe654QjMCW9qnVFvz3egV", "dur": 203, "ts": 1637081458.212, "upload_date": "2021-11-16", "category": "hot", "local_check_ts": null, "public_check_ts": 1637307537.0622492, "local_data": null, "public_data": {"overhead": 0.19189, "download_time": 1.6514600000000002, "file_size": 29989910.0, "video_length": 203, "stall_rate": 0, "bandwidth": 18159634.505225677}}, {"cid": "Qmd9YKvZtmtJuJBLYR3eMUWPmfgDPkze1AY8pfnxAbueq9", "dur": 278, "ts": 1637052752.131, "upload_date": "2021-11-16", "category": "hot", "local_check_ts": null, "public_check_ts": 1637307661.2454472, "local_data": null, "public_data": {"overhead": 0.131702, "download_time": 3.400463, "file_size": 58068063.0, "video_length": 278, "stall_rate": 0, "bandwidth": 17076516.63905768}}, {"cid": "QmcPx4kKtBgQ2LGBZ7cGApFBFZKBHDM4o3DZ5FJWwsVGpd", "dur": 965, "ts": 1637171747.467, "upload_date": "2021-11-17", "category": "trending", "local_check_ts": null, "public_check_ts": 1637307796.7453823, "local_data": null, "public_data": {"overhead": 1.223137, "download_time": 13.324615, "file_size": 167815623.0, "video_length": 965, "stall_rate": 0, "bandwidth": 12594406.892807035}}, {"cid": "Qmczs1jnF3tbHULZcHrenn2sVCZYtBUTjqsffSyhwnmr51", "dur": 1005, "ts": 1637187334.198, "upload_date": "2021-11-17", "category": "trending", "local_check_ts": null, "public_check_ts": 1637307923.81307, "local_data": null, "public_data": {"overhead": 0.172631, "download_time": 6.51307, "file_size": 105805377.0, "video_length": 1005, "stall_rate": 0, "bandwidth": 16245085.190240547}}, {"cid": "QmRC81DKjZ55HA3LnvEe4MpSUfeA6b5WufAUNCGgzdmxhg", "dur": 570, "ts": 1637189240.273, "upload_date": "2021-11-17", "category": "new", "local_check_ts": null, "public_check_ts": 1637308049.4008589, "local_data": null, "public_data": {"overhead": 0.427606, "download_time": 4.546534, "file_size": 82588862.0, "video_length": 570, "stall_rate": 0, "bandwidth": 18165235.75981176}}, {"cid": "QmdMYe1NCfnkDmmbPo7NJKDh39B6DrYNhsTrVmBMa7xwC7", "dur": 235, "ts": 1637187621.162, "upload_date": "2021-11-17", "category": "new", "local_check_ts": null, "public_check_ts": 1637308172.7751927, "local_data": null, "public_data": {"overhead": 0.183933, "download_time": 2.242848, "file_size": 38785811.0, "video_length": 235, "stall_rate": 0, "bandwidth": 17293107.245787498}}, {"cid": "QmXfyaYx9yBNfWYof5LtoQgiePk4WjHY223EQxMPohypki", "dur": 316, "ts": 1637187119.727, "upload_date": "2021-11-17", "category": "new", "local_check_ts": null, "public_check_ts": 1637308293.7775116, "local_data": null, "public_data": {"overhead": 0.178145, "download_time": 0.0008460000000000134, "file_size": 169.0, "video_length": 316, "stall_rate": 0, "bandwidth": 199763.59338061148}}, {"cid": "QmXzhpfLdzAMWSqiyPcjK3S9A3VGy7Jw46Zab6Mv2KiqHk", "dur": 100, "ts": 1637186150.12, "upload_date": "2021-11-17", "category": "new", "local_check_ts": 1637308341.0166814, "public_check_ts": 1637308341.9477813, "local_data": {"overhead": 12.965047, "download_time": 33.450641000000005, "file_size": 10830948.0, "video_length": 100, "stall_rate": 0, "bandwidth": 323788.952205729}, "public_data": {"overhead": 0.174185, "download_time": 0.0008370000000000044, "file_size": 169.0, "video_length": 100, "stall_rate": 0, "bandwidth": 201911.58900836215}}, {"cid": "QmZjiyfLf7gMRpwT3HyZUBe141F3XZADF3brahSAFkiUTX", "dur": 294, "ts": 1637181942.288, "upload_date": "2021-11-17", "category": "new", "local_check_ts": null, "public_check_ts": 1637308465.5762193, "local_data": null, "public_data": {"overhead": 0.159897, "download_time": 2.443121, "file_size": 43869220.0, "video_length": 294, "stall_rate": 0, "bandwidth": 17956220.752062626}}, {"cid": "QmX9X726caSfrGRvhjSdefm7p9SESz6ztXxZaE3cLdLjPr", "dur": 11, "ts": 1637175629.074, "upload_date": "2021-11-17", "category": "new", "local_check_ts": null, "public_check_ts": 1637308586.2626884, "local_data": null, "public_data": {"overhead": 0.158531, "download_time": 0.243524, "file_size": 1709994.0, "video_length": 11, "stall_rate": 0, "bandwidth": 7021870.534321053}}, {"cid": "QmVhdEfbQHroHMGjxWThLedCSpamN7o685SiDX5oBktfsi", "dur": 44, "ts": 1637165162.28, "upload_date": "2021-11-17", "category": "hot", "local_check_ts": null, "public_check_ts": 1637308707.848148, "local_data": null, "public_data": {"overhead": 0.288293, "download_time": 0.49712599999999996, "file_size": 6252607.0, "video_length": 44, "stall_rate": 0, "bandwidth": 12577509.524748255}}, {"cid": "QmXq8eDahPrLMgY9VGkjFWAzEbMmoNji5RSqSdB7dZV3hq", "dur": 305, "ts": 1637144434.299, "upload_date": "2021-11-17", "category": "hot", "local_check_ts": null, "public_check_ts": 1637308831.4067817, "local_data": null, "public_data": {"overhead": 0.206266, "download_time": 2.94171, "file_size": 44644016.0, "video_length": 305, "stall_rate": 0, "bandwidth": 15176212.475057025}}, {"cid": "QmSeX7fnJ1iMmFuBhTphNeG4hJ9GmZbpd3pd3N7kxs7HaM", "dur": 418, "ts": 1637168910.969, "upload_date": "2021-11-17", "category": "hot", "local_check_ts": null, "public_check_ts": 1637308954.4668992, "local_data": null, "public_data": {"overhead": 2.640995, "download_time": 0.0006769999999995946, "file_size": 169.0, "video_length": 418, "stall_rate": 0, "bandwidth": 249630.72378153796}}, {"cid": "QmSnWonFytzhREsjUXYS4vFFLANGCffF1h5S9LDTzKZxcB", "dur": 370, "ts": 1637216233.181, "upload_date": "2021-11-18", "category": "trending", "local_check_ts": 1637280082.528148, "public_check_ts": 1637280083.1718462, "local_data": {"overhead": 1.380426, "download_time": 67.131542, "file_size": 237335593.0, "video_length": 370, "stall_rate": 0, "bandwidth": 3535381.2221384696}, "public_data": {"overhead": 0.070082, "download_time": 0.0006509999999999988, "file_size": 169.0, "video_length": 370, "stall_rate": 0, "bandwidth": 259600.6144393246}}, {"cid": "QmQpgYWkUtwPxYdwjYCK3PbSfAdSLRWnEEzU2i58evUQR2", "dur": 171, "ts": 1636968534.756, "upload_date": "2021-11-15", "category": "trending", "local_check_ts": null, "public_check_ts": 1637280249.0656438, "local_data": null, "public_data": {"overhead": 1.664379, "download_time": 43.107471000000004, "file_size": 24346233.0, "video_length": 171, "stall_rate": 0, "bandwidth": 564779.8962736644}}, {"cid": "QmQm3coFRysZSHtvimRezBZVxjCgTb9TT2yacbd4juM8rS", "dur": 267, "ts": 1637256233.081, "upload_date": "2021-11-18", "category": "trending", "local_check_ts": null, "public_check_ts": 1637280411.9391463, "local_data": null, "public_data": {"overhead": 0.577039, "download_time": 41.733487000000004, "file_size": 39777863.0, "video_length": 267, "stall_rate": 0, "bandwidth": 953140.1725429748}}, {"cid": "QmdwuGvmB5wTEyhEEPDqHsGTjTwJz1ySpE5emjuatXLUaQ", "dur": 211, "ts": 1637166905.226, "upload_date": "2021-11-17", "category": "trending", "local_check_ts": null, "public_check_ts": 1637280657.0634604, "local_data": null, "public_data": {"overhead": 14.308071, "download_time": 109.79787, "file_size": 47585294.0, "video_length": 211, "stall_rate": 0, "bandwidth": 433389.9555610687}}, {"cid": "QmRRvQv3z4TPazjqrsCjhsiVW3kJRiVPDgUppaiHr9eyeY", "dur": 58, "ts": 1637209853.557, "upload_date": "2021-11-18", "category": "trending", "local_check_ts": null, "public_check_ts": 1637280862.6655207, "local_data": null, "public_data": {"overhead": 16.224749, "download_time": 68.930255, "file_size": 7315880.0, "video_length": 58, "stall_rate": 0.18845267241379315, "bandwidth": 106134.52684891416}}, {"cid": "Qmcy9mwve9n1Gv4N62VGL8BxDXqZHgsdwCA7jYkeZJQHYk", "dur": 321, "ts": 1637018252.31, "upload_date": "2021-11-15", "category": "trending", "local_check_ts": null, "public_check_ts": 1637281108.320215, "local_data": null, "public_data": {"overhead": 1.095715, "download_time": 123.39476, "file_size": 47628908.0, "video_length": 321, "stall_rate": 0, "bandwidth": 385988.0922009978}}, {"cid": "Qmc4PvsT8r3a5EPCSdBBgHdXmVe7Z7Kt5UVNmewCrBNYgC", "dur": 333, "ts": 1637117371.634, "upload_date": "2021-11-17", "category": "trending", "local_check_ts": 1637281132.9105458, "public_check_ts": 1637281133.9354622, "local_data": {"overhead": 0.761358, "download_time": 23.56232, "file_size": 207541890.0, "video_length": 333, "stall_rate": 0, "bandwidth": 8808211.160870407}, "public_data": {"overhead": 0.197322, "download_time": 0.0006400000000000017, "file_size": 169.0, "video_length": 333, "stall_rate": 0, "bandwidth": 264062.4999999993}}, {"cid": "QmQEjS6GWjAUyfDVDSBPF1hAZWL6psH9vs5V7dv325VynR", "dur": 42, "ts": 1637224570.446, "upload_date": "2021-11-18", "category": "trending", "local_check_ts": null, "public_check_ts": 1637281268.189023, "local_data": null, "public_data": {"overhead": 0.939416, "download_time": 12.314324000000001, "file_size": 6188900.0, "video_length": 42, "stall_rate": 0, "bandwidth": 502577.3237735177}}, {"cid": "Qmf7VwT6XdHtdMW6U3hPvCRhhEVLs4rLBPRdBZG3Zh1SR6", "dur": 82, "ts": 1637201588.983, "upload_date": "2021-11-18", "category": "trending", "local_check_ts": null, "public_check_ts": 1637281412.763899, "local_data": null, "public_data": {"overhead": 0.486451, "download_time": 23.126917000000002, "file_size": 11621497.0, "video_length": 82, "stall_rate": 0, "bandwidth": 502509.5649368223}}, {"cid": "QmS6qumm8K4afNQATTHRjNnXy3LTP5TPj5RH4TVqTxnBFx", "dur": 108, "ts": 1637276085.227, "upload_date": "2021-11-18", "category": "new", "local_check_ts": null, "public_check_ts": 1637281569.6273167, "local_data": null, "public_data": {"overhead": 0.531541, "download_time": 35.712671, "file_size": 15363494.0, "video_length": 108, "stall_rate": 0, "bandwidth": 430197.2820795174}}, {"cid": "QmXZxRz2xczpP9eTuxBtoDdyKoCSS8tHGx7GzrALKuxjFM", "dur": 196, "ts": 1637275544.549, "upload_date": "2021-11-18", "category": "new", "local_check_ts": null, "public_check_ts": 1637281711.7619522, "local_data": null, "public_data": {"overhead": 2.749695, "download_time": 18.400313, "file_size": 12701759.0, "video_length": 196, "stall_rate": 0, "bandwidth": 690301.2465059698}}, {"cid": "QmSXufSYQWB6GNcmWtBvfmDbwGqHmSpk266dur53Xmzsxp", "dur": 65, "ts": 1637273668.682, "upload_date": "2021-11-18", "category": "new", "local_check_ts": null, "public_check_ts": 1637281834.234965, "local_data": null, "public_data": {"overhead": 0.311257, "download_time": 1.024839, "file_size": 1761881.0, "video_length": 65, "stall_rate": 0, "bandwidth": 1719178.3294741905}}, {"cid": "QmYyYE5cXcHVoQAJCCdiQ5d6sCTTfZstWiAhG5H3MArjwv", "dur": 12083, "ts": 1637272043.284, "upload_date": "2021-11-18", "category": "new", "local_check_ts": null, "public_check_ts": 1637281955.409927, "local_data": null, "public_data": {"overhead": 0.166359, "download_time": 0.0007840000000000069, "file_size": 169.0, "video_length": 12083, "stall_rate": 0, "bandwidth": 215561.22448979403}}, {"cid": "QmcEWFepeu6oSrmSqvzcHSuXwAyu9aomJAzTkAZ24ySwfa", "dur": 5541, "ts": 1637267294.799, "upload_date": "2021-11-18", "category": "new", "local_check_ts": null, "public_check_ts": 1637282076.551453, "local_data": null, "public_data": {"overhead": 0.130506, "download_time": 0.0008269999999999944, "file_size": 169.0, "video_length": 5541, "stall_rate": 0, "bandwidth": 204353.08343410052}}, {"cid": "QmeieLiHnQVimsLvGXJ2XpKXmZAikmwfS8Z6GYq37Nmo9e", "dur": 311, "ts": 1637265065.586, "upload_date": "2021-11-18", "category": "new", "local_check_ts": null, "public_check_ts": 1637282203.0824301, "local_data": null, "public_data": {"overhead": 0.23356, "download_time": 5.2600940000000005, "file_size": 56998416.0, "video_length": 311, "stall_rate": 0, "bandwidth": 10836007.113180866}}, {"cid": "QmQBvPTHYCoTUPBRcd3e6FQj5L6Ncck67YCeyNbugmwQeo", "dur": 333, "ts": 1637264739.305, "upload_date": "2021-11-18", "category": "new", "local_check_ts": null, "public_check_ts": 1637282372.9291525, "local_data": null, "public_data": {"overhead": 0.714131, "download_time": 48.225488999999996, "file_size": 60360010.0, "video_length": 333, "stall_rate": 0, "bandwidth": 1251620.4864195364}}, {"cid": "QmRMA86qfZ8NEh5QuBUHzKCkV7X8qnnmP8Ap4Z2zKNEtkF", "dur": 301, "ts": 1637264322.44, "upload_date": "2021-11-18", "category": "new", "local_check_ts": null, "public_check_ts": 1637282538.1604319, "local_data": null, "public_data": {"overhead": 3.814086, "download_time": 40.803681, "file_size": 42218192.0, "video_length": 301, "stall_rate": 0, "bandwidth": 1034666.2596445649}}, {"cid": "QmUmkEvW21RyESyyuP94r35135jMNuJicL9bcNYYw8a27w", "dur": 325, "ts": 1637262600.63, "upload_date": "2021-11-18", "category": "new", "local_check_ts": null, "public_check_ts": 1637282682.1897278, "local_data": null, "public_data": {"overhead": 0.292811, "download_time": 22.81404, "file_size": 45338687.0, "video_length": 325, "stall_rate": 0, "bandwidth": 1987315.1357672734}}, {"cid": "QmPD4JTXTeoBNFMXrMoJuMZLdjyz3YyhKe65syMdPqB4Qh", "dur": 305, "ts": 1637261806.176, "upload_date": "2021-11-18", "category": "new", "local_check_ts": null, "public_check_ts": 1637282810.654297, "local_data": null, "public_data": {"overhead": 0.480923, "download_time": 7.500368, "file_size": 42777130.0, "video_length": 305, "stall_rate": 0, "bandwidth": 5703337.489573845}}, {"cid": "QmPrDgjuZwkoGN1xysMUhqPQQS7n9NBdneic23Ha6btAvV", "dur": 229, "ts": 1637261183.923, "upload_date": "2021-11-18", "category": "new", "local_check_ts": null, "public_check_ts": 1637282950.5689123, "local_data": null, "public_data": {"overhead": 0.331498, "download_time": 19.247153, "file_size": 32757005.0, "video_length": 229, "stall_rate": 0, "bandwidth": 1701914.303897309}}, {"cid": "QmQm3coFRysZSHtvimRezBZVxjCgTb9TT2yacbd4juM8rS", "dur": 267, "ts": 1637256233.081, "upload_date": "2021-11-18", "category": "hot", "local_check_ts": null, "public_check_ts": 1637283090.9065285, "local_data": null, "public_data": {"overhead": 0.987791, "download_time": 18.731264, "file_size": 39777863.0, "video_length": 267, "stall_rate": 0, "bandwidth": 2123608.049088412}}, {"cid": "QmcEWFepeu6oSrmSqvzcHSuXwAyu9aomJAzTkAZ24ySwfa", "dur": 5541, "ts": 1637267294.799, "upload_date": "2021-11-18", "category": "hot", "local_check_ts": null, "public_check_ts": 1637283211.6927829, "local_data": null, "public_data": {"overhead": 0.116238, "download_time": 0.0006230000000000124, "file_size": 169.0, "video_length": 5541, "stall_rate": 0, "bandwidth": 271268.0577849063}}, {"cid": "QmSnWonFytzhREsjUXYS4vFFLANGCffF1h5S9LDTzKZxcB", "dur": 370, "ts": 1637216233.181, "upload_date": "2021-11-18", "category": "hot", "local_check_ts": 1637283224.778346, "public_check_ts": 1637283225.6181583, "local_data": {"overhead": 0.219407, "download_time": 11.980554999999999, "file_size": 237335593.0, "video_length": 370, "stall_rate": 0, "bandwidth": 19810066.64549347}, "public_data": {"overhead": 0.117114, "download_time": 0.0005350000000000077, "file_size": 169.0, "video_length": 370, "stall_rate": 0, "bandwidth": 315887.8504672852}}, {"cid": "QmQEjS6GWjAUyfDVDSBPF1hAZWL6psH9vs5V7dv325VynR", "dur": 42, "ts": 1637224570.446, "upload_date": "2021-11-18", "category": "hot", "local_check_ts": null, "public_check_ts": 1637283361.6959305, "local_data": null, "public_data": {"overhead": 3.540438, "download_time": 11.461093, "file_size": 6188900.0, "video_length": 42, "stall_rate": 0, "bandwidth": 539992.1281504303}}, {"cid": "QmRRvQv3z4TPazjqrsCjhsiVW3kJRiVPDgUppaiHr9eyeY", "dur": 58, "ts": 1637209853.557, "upload_date": "2021-11-18", "category": "hot", "local_check_ts": null, "public_check_ts": 1637283502.8838954, "local_data": null, "public_data": {"overhead": 0.716796, "download_time": 19.296299, "file_size": 7315880.0, "video_length": 58, "stall_rate": 0, "bandwidth": 379133.84323076665}}, {"cid": "QmccyhJDyz72ftGfMZPRRiGiz5v8LGfEG3U1u4mqBdJVr5", "dur": 378, "ts": 1637228026.275, "upload_date": "2021-11-18", "category": "hot", "local_check_ts": null, "public_check_ts": 1637283765.1401541, "local_data": null, "public_data": {"overhead": 0.330848, "download_time": 141.611268, "file_size": 79279463.0, "video_length": 378, "stall_rate": 0, "bandwidth": 559838.6634035365}}]